{
  "$schema": "https://pitsiui.com/schema/registry-item.json",
  "name": "app-database-tables-1",
  "type": "registry:block",
  "description": "Database tables list with details panel",
  "dependencies": [
    "lucide-react"
  ],
  "registryDependencies": [
    "badge",
    "button",
    "card",
    "input",
    "utils"
  ],
  "files": [
    {
      "path": "registry/new-york-v4/blocks/application/app-database-tables-1.tsx",
      "content": "\"use client\"\n\nimport * as React from \"react\"\nimport { ChevronRight, Plus, Search, Table } from \"lucide-react\"\n\nimport { cn } from \"@/lib/utils\"\nimport { Badge } from \"@/registry/new-york-v4/ui/badge\"\nimport { Button } from \"@/registry/new-york-v4/ui/button\"\nimport {\n  Card,\n  CardContent,\n  CardHeader,\n  CardTitle,\n} from \"@/registry/new-york-v4/ui/card\"\nimport { Input } from \"@/registry/new-york-v4/ui/input\"\n\nconst tables = [\n  {\n    name: \"users\",\n    rows: 45230,\n    columns: 12,\n    size: \"1.2 GB\",\n    lastUpdated: \"2 min ago\",\n    status: \"active\",\n  },\n  {\n    name: \"products\",\n    rows: 8450,\n    columns: 18,\n    size: \"450 MB\",\n    lastUpdated: \"1 hour ago\",\n    status: \"active\",\n  },\n  {\n    name: \"orders\",\n    rows: 124500,\n    columns: 15,\n    size: \"2.1 GB\",\n    lastUpdated: \"5 min ago\",\n    status: \"active\",\n  },\n  {\n    name: \"inventory\",\n    rows: 12300,\n    columns: 8,\n    size: \"280 MB\",\n    lastUpdated: \"3 hours ago\",\n    status: \"active\",\n  },\n  {\n    name: \"customers\",\n    rows: 32100,\n    columns: 14,\n    size: \"890 MB\",\n    lastUpdated: \"10 min ago\",\n    status: \"active\",\n  },\n  {\n    name: \"transactions\",\n    rows: 89000,\n    columns: 10,\n    size: \"1.8 GB\",\n    lastUpdated: \"1 min ago\",\n    status: \"active\",\n  },\n  {\n    name: \"logs_archive\",\n    rows: 500000,\n    columns: 6,\n    size: \"3.2 GB\",\n    lastUpdated: \"1 day ago\",\n    status: \"archived\",\n  },\n  {\n    name: \"sessions\",\n    rows: 2400,\n    columns: 5,\n    size: \"45 MB\",\n    lastUpdated: \"30 sec ago\",\n    status: \"active\",\n  },\n]\n\ninterface DatabaseTablesProps {\n  onSelectTable?: (tableName: string) => void\n}\n\nexport function AppDatabaseTables1({ onSelectTable }: DatabaseTablesProps) {\n  const [search, setSearch] = React.useState(\"\")\n  const [selectedTable, setSelectedTable] = React.useState<string | null>(null)\n\n  const filteredTables = tables.filter((table) =>\n    table.name.toLowerCase().includes(search.toLowerCase())\n  )\n\n  const handleSelectTable = (tableName: string) => {\n    setSelectedTable(tableName)\n    onSelectTable?.(tableName)\n  }\n\n  const selected = tables.find((t) => t.name === selectedTable)\n\n  return (\n    <div className=\"p-4\">\n      <div className=\"mx-auto max-w-5xl space-y-4\">\n        <div className=\"flex items-center justify-between\">\n          <div>\n            <h1 className=\"text-foreground text-3xl font-bold tracking-tight\">\n              Tables\n            </h1>\n            <p className=\"text-muted-foreground\">\n              Browse and manage database tables\n            </p>\n          </div>\n          <Button>\n            <Plus className=\"mr-2 size-4\" />\n            Create Table\n          </Button>\n        </div>\n\n        <div className=\"relative\">\n          <Search className=\"text-muted-foreground absolute top-1/2 left-3 size-4 -translate-y-1/2\" />\n          <Input\n            placeholder=\"Search tables...\"\n            value={search}\n            onChange={(e) => setSearch(e.target.value)}\n            className=\"pl-9\"\n          />\n        </div>\n\n        <div className=\"grid gap-4 lg:grid-cols-[1fr_350px]\">\n          <Card>\n            <CardHeader>\n              <CardTitle className=\"text-base\">\n                All Tables ({filteredTables.length})\n              </CardTitle>\n            </CardHeader>\n            <CardContent className=\"p-0\">\n              <div className=\"divide-y\">\n                {filteredTables.map((table) => (\n                  <button\n                    key={table.name}\n                    onClick={() => handleSelectTable(table.name)}\n                    className={cn(\n                      \"flex w-full items-center gap-4 p-4 text-left transition-colors\",\n                      selectedTable === table.name\n                        ? \"bg-muted\"\n                        : \"hover:bg-muted/50\"\n                    )}\n                  >\n                    <div className=\"bg-muted flex size-10 items-center justify-center rounded-lg\">\n                      <Table className=\"text-muted-foreground size-5\" />\n                    </div>\n                    <div className=\"min-w-0 flex-1\">\n                      <div className=\"flex items-center gap-2\">\n                        <p className=\"font-medium\">{table.name}</p>\n                        <Badge\n                          variant={\n                            table.status === \"active\" ? \"default\" : \"secondary\"\n                          }\n                        >\n                          {table.status}\n                        </Badge>\n                      </div>\n                      <p className=\"text-muted-foreground text-sm\">\n                        {table.rows.toLocaleString()} rows · {table.columns}{\" \"}\n                        columns\n                      </p>\n                    </div>\n                    <div className=\"text-right\">\n                      <p className=\"text-sm font-medium\">{table.size}</p>\n                      <p className=\"text-muted-foreground text-xs\">\n                        {table.lastUpdated}\n                      </p>\n                    </div>\n                    <ChevronRight className=\"text-muted-foreground size-4\" />\n                  </button>\n                ))}\n              </div>\n            </CardContent>\n          </Card>\n\n          <Card className=\"h-fit\">\n            <CardHeader>\n              <CardTitle className=\"text-base\">Table Details</CardTitle>\n            </CardHeader>\n            <CardContent>\n              {selected ? (\n                <div className=\"space-y-4\">\n                  <div className=\"flex items-center gap-3\">\n                    <div className=\"bg-muted flex size-12 items-center justify-center rounded-lg\">\n                      <Table className=\"text-muted-foreground size-6\" />\n                    </div>\n                    <div>\n                      <p className=\"font-semibold\">{selected.name}</p>\n                      <Badge\n                        variant={\n                          selected.status === \"active\" ? \"default\" : \"secondary\"\n                        }\n                      >\n                        {selected.status}\n                      </Badge>\n                    </div>\n                  </div>\n\n                  <div className=\"grid grid-cols-2 gap-4\">\n                    <div className=\"space-y-1\">\n                      <p className=\"text-muted-foreground text-xs\">Rows</p>\n                      <p className=\"text-xl font-bold\">\n                        {selected.rows.toLocaleString()}\n                      </p>\n                    </div>\n                    <div className=\"space-y-1\">\n                      <p className=\"text-muted-foreground text-xs\">Columns</p>\n                      <p className=\"text-xl font-bold\">{selected.columns}</p>\n                    </div>\n                  </div>\n\n                  <div className=\"space-y-2 border-t pt-4\">\n                    <div className=\"flex justify-between text-sm\">\n                      <span className=\"text-muted-foreground\">Size</span>\n                      <span className=\"font-medium\">{selected.size}</span>\n                    </div>\n                    <div className=\"flex justify-between text-sm\">\n                      <span className=\"text-muted-foreground\">\n                        Last Updated\n                      </span>\n                      <span className=\"font-medium\">\n                        {selected.lastUpdated}\n                      </span>\n                    </div>\n                  </div>\n\n                  <div className=\"flex gap-2\">\n                    <Button variant=\"outline\" className=\"flex-1\">\n                      View Data\n                    </Button>\n                    <Button variant=\"outline\" className=\"flex-1\">\n                      Query\n                    </Button>\n                  </div>\n                </div>\n              ) : (\n                <div className=\"text-muted-foreground py-8 text-center\">\n                  <Table className=\"mx-auto mb-2 size-8 opacity-30\" />\n                  <p className=\"text-sm\">Select a table to view details</p>\n                </div>\n              )}\n            </CardContent>\n          </Card>\n        </div>\n      </div>\n    </div>\n  )\n}\n",
      "type": "registry:block"
    }
  ],
  "categories": [
    "application",
    "app-database"
  ],
  "tier": "free",
  "readiness": "beta"
}