{
  "$schema": "https://ui.pitsi.com/schema/registry-item.json",
  "name": "e-commerce-product-overview-with-image-gallery-and-description",
  "type": "registry:block",
  "description": "A with image gallery and description block.",
  "files": [
    {
      "path": "registry/new-york-v4/blocks/e-commerce/product-overview/with-image-gallery-and-description.tsx",
      "content": "export default function WithImageGalleryAndDescription() {\n  return (\n    <section className=\"relative py-10 lg:py-24\">\n      <div className=\"mx-auto max-w-7xl px-4 sm:px-6 lg:px-8\">\n        <div className=\"grid grid-cols-1 gap-8 lg:grid-cols-2 lg:gap-16\">\n          <div className=\"pro-detail order-last flex w-full flex-col justify-center max-lg:mx-auto max-lg:max-w-[608px] lg:order-none\">\n            <p className=\"mb-4 text-lg font-medium text-indigo-600\">\n              Travel &nbsp; / &nbsp; Menswear\n            </p>\n            <h2 className=\"font-manrope mb-2 text-3xl leading-10 font-bold text-gray-900\">\n              Yellow Summer Travel Bag\n            </h2>\n            <div className=\"mb-6 flex flex-col sm:flex-row sm:items-center\">\n              <h6 className=\"font-manrope mr-5 border-gray-200 pr-5 text-2xl leading-9 font-semibold text-gray-900 sm:border-r\">\n                $220\n              </h6>\n              <div className=\"flex items-center gap-2\">\n                <div className=\"flex items-center gap-1\"></div>\n                <span className=\"pl-2 text-sm leading-7 font-normal text-gray-500\">\n                  1624 review\n                </span>\n              </div>\n            </div>\n            <p className=\"mb-8 text-base font-normal text-gray-500\">\n              the perfect companion for your next adventure! Embrace the spirit\n              of sunny escapades with this vibrant and versatile bag designed to\n              cater to your travel needs while adding a pop of color to your\n              journey.\n            </p>\n            <div className=\"block w-full\">\n              <p className=\"mb-4 text-lg leading-8 font-medium text-gray-900\">\n                Bag Color\n              </p>\n              <div className=\"text\">\n                <div className=\"relative mb-6 flex items-center justify-start gap-3 md:gap-6\">\n                  <button\n                    data-ui=\"checked active\"\n                    className=\":border-emerald-500 rounded-full border border-gray-200 p-2.5 transition-all duration-300 hover:border-emerald-500\"\n                  ></button>\n                  <button className=\"rounded-full border border-gray-200 p-2.5 transition-all duration-300 focus-within:border-amber-400 hover:border-amber-400\"></button>\n                  <button className=\"rounded-full border border-gray-200 p-2.5 transition-all duration-300 focus-within:border-red-500 hover:border-red-500\"></button>\n                  <button className=\"rounded-full border border-gray-200 p-2.5 transition-all duration-300 focus-within:border-blue-400 hover:border-blue-400\"></button>\n                </div>\n                <div className=\"mb-6 block w-full\">\n                  <p className=\"mb-4 text-lg leading-8 font-medium text-gray-900\">\n                    Bag size\n                  </p>\n                  <div className=\"grid grid-cols-2 gap-3 min-[400px]:grid-cols-3\">\n                    <button className=\"w-full rounded-full border border-gray-200 px-1.5 py-2 text-lg font-semibold whitespace-nowrap text-gray-900 shadow-sm shadow-transparent transition-all duration-300 hover:border-gray-300 hover:bg-gray-50 hover:shadow-gray-300 sm:px-6\">\n                      56 cm (S)\n                    </button>\n                    <button className=\"w-full rounded-full border border-gray-200 px-1.5 py-2 text-lg font-semibold whitespace-nowrap text-gray-900 shadow-sm shadow-transparent transition-all duration-300 hover:border-gray-300 hover:bg-gray-50 hover:shadow-gray-300 sm:px-6\">\n                      67 cm (M)\n                    </button>\n                    <button className=\"w-full rounded-full border border-gray-200 px-1.5 py-2 text-lg font-semibold whitespace-nowrap text-gray-900 shadow-sm shadow-transparent transition-all duration-300 hover:border-gray-300 hover:bg-gray-50 hover:shadow-gray-300 sm:px-6\">\n                      77 cm (L)\n                    </button>\n                  </div>\n                </div>\n                <div className=\"mb-8 grid grid-cols-1 gap-3 sm:grid-cols-2\">\n                  <div className=\"flex w-full items-center justify-center\">\n                    <button className=\"group rounded-l-full border border-gray-400 px-6 py-4 shadow-sm shadow-transparent transition-all duration-500 hover:bg-gray-50 hover:shadow-gray-300\"></button>\n                    <input\n                      type=\"text\"\n                      className=\"w-full border-y border-gray-400 bg-transparent px-6 py-[13px] text-center text-lg font-semibold text-gray-900 outline-0 placeholder:text-gray-900 focus-within:bg-gray-50 hover:bg-gray-50 lg:max-w-[118px]\"\n                    />\n                    <button className=\"group rounded-r-full border border-gray-400 px-6 py-4 shadow-sm shadow-transparent transition-all duration-500 hover:bg-gray-50 hover:shadow-gray-300\"></button>\n                  </div>\n                  <button className=\"group flex w-full items-center justify-center gap-2 rounded-full bg-indigo-50 px-5 py-4 text-lg font-semibold text-indigo-600 shadow-sm shadow-transparent transition-all duration-500 hover:bg-indigo-100 hover:shadow-indigo-200\">\n                    Add to cart\n                  </button>\n                </div>\n                <div className=\"flex items-center gap-3\">\n                  <button className=\"group rounded-full bg-indigo-50 p-4 transition-all duration-500 hover:bg-indigo-100 hover:shadow-sm hover:shadow-indigo-300\"></button>\n                  <button className=\"flex w-full items-center justify-center rounded-[100px] bg-indigo-600 px-5 py-4 text-center text-lg font-semibold text-white shadow-sm transition-all duration-500 hover:bg-indigo-700 hover:shadow-indigo-400\">\n                    Buy Now\n                  </button>\n                </div>\n              </div>\n            </div>\n          </div>\n          <div>\n            <div className=\"swiper product-prev mb-6\">\n              <div className=\"swiper-wrapper\">\n                <div className=\"swiper-slide\">\n                  <img\n                    src=\"https://pagedone.io/asset/uploads/1700471851.png\"\n                    alt=\"Yellow Travel Bag image\"\n                    className=\"mx-auto object-cover\"\n                  />\n                </div>\n                <div className=\"swiper-slide\">\n                  <img\n                    src=\"https://pagedone.io/asset/uploads/1711514857.png\"\n                    alt=\"Yellow Travel Bag image\"\n                    className=\"mx-auto object-cover\"\n                  />\n                </div>\n                <div className=\"swiper-slide\">\n                  <img\n                    src=\"https://pagedone.io/asset/uploads/1711514875.png\"\n                    alt=\"Yellow Travel Bag image\"\n                    className=\"mx-auto object-cover\"\n                  />\n                </div>\n                <div className=\"swiper-slide\">\n                  <img\n                    src=\"https://pagedone.io/asset/uploads/1711514892.png\"\n                    alt=\"Yellow Travel Bag image\"\n                    className=\"mx-auto object-cover\"\n                  />\n                </div>\n              </div>\n            </div>\n            <div className=\"swiper product-thumb mx-auto max-w-[608px]\">\n              <div className=\"swiper-wrapper\">\n                <div className=\"swiper-slide\">\n                  <img\n                    src=\"https://pagedone.io/asset/uploads/1700471871.png\"\n                    alt=\"Travel Bag image\"\n                    className=\"slide:border-indigo-600 cursor-pointer border-2 border-gray-50 object-cover transition-all duration-500 hover:border-indigo-600\"\n                  />\n                </div>\n                <div className=\"swiper-slide\">\n                  <img\n                    src=\"https://pagedone.io/asset/uploads/1711514930.png\"\n                    alt=\"Travel Bag image\"\n                    className=\"slide:border-indigo-600 cursor-pointer border-2 border-gray-50 object-cover transition-all duration-500 hover:border-indigo-600\"\n                  />\n                </div>\n                <div className=\"swiper-slide\">\n                  <img\n                    src=\"https://pagedone.io/asset/uploads/1700471908.png\"\n                    alt=\"Travel Bag image\"\n                    className=\"slide:border-indigo-600 cursor-pointer border-2 border-gray-50 object-cover transition-all duration-500 hover:border-indigo-600\"\n                  />\n                </div>\n                <div className=\"swiper-slide\">\n                  <img\n                    src=\"https://pagedone.io/asset/uploads/1700471925.png\"\n                    alt=\"Travel Bag image\"\n                    className=\"slide:border-indigo-600 cursor-pointer border-2 border-gray-50 object-cover transition-all duration-500 hover:border-indigo-600\"\n                  />\n                </div>\n              </div>\n            </div>\n          </div>\n        </div>\n      </div>\n    </section>\n  )\n}\n",
      "type": "registry:block"
    }
  ],
  "categories": [
    "e-commerce"
  ],
  "tier": "pro",
  "readiness": "alpha"
}