{
  "$schema": "https://pitsiui.com/schema/registry-item.json",
  "name": "marketing-integration-vertical-integrations-list",
  "type": "registry:block",
  "description": "A vertical integrations list block.",
  "files": [
    {
      "path": "registry/new-york-v4/blocks/marketing/integration/vertical-integrations-list.tsx",
      "content": "export default function VerticalIntegrationsList() {\n  return (\n    <section className=\"relative py-24\">\n      <div className=\"mx-auto w-full max-w-7xl px-4 md:px-5 lg:px-5\">\n        <div className=\"inline-flex w-full flex-col items-center justify-start gap-10\">\n          <div className=\"flex flex-col items-center justify-start gap-8 lg:flex-row lg:gap-12\">\n            <div className=\"inline-flex flex-col items-start justify-center gap-2.5\">\n              <h2 className=\"font-manrope w-full text-center text-3xl leading-normal font-bold text-gray-900 lg:text-start\">\n                Integrate Your Key Apps\n              </h2>\n              <p className=\"text-center text-base leading-relaxed font-normal text-gray-500 lg:text-start\">\n                Integrate your essential applications seamlessly, creating a\n                cohesive digital ecosystem tailored to your needs. By linking\n                these key apps, you establish a unified workflow, ensuring\n                smoother data exchange and enhanced collaboration among your\n                preferred tools.\n              </p>\n            </div>\n            <button className=\"flex w-full items-center justify-center rounded-lg bg-gradient-to-r from-gray-700 to-gray-500 px-3.5 py-2 shadow-[0px_1px_2px_0px_rgba(16,_24,_40,_0.05)] transition-all duration-700 ease-in-out hover:from-gray-800 hover:to-gray-600 sm:w-fit\">\n              <span className=\"px-1.5 text-sm leading-6 font-medium whitespace-nowrap text-white\">\n                All Integration\n              </span>\n            </button>\n          </div>\n          <div className=\"flex w-full flex-col items-center justify-start gap-6\">\n            <div className=\"flex w-full flex-col items-start justify-center gap-6\">\n              <div className=\"group flex w-full flex-col items-start justify-center gap-3.5 rounded-xl border border-gray-200 bg-white p-5 transition-all duration-700 ease-in-out hover:border-gray-700 hover:bg-gray-50\">\n                <div className=\"inline-flex items-center justify-start gap-2\">\n                  {/* SVG removed */}\n                  <h4 className=\"text-lg leading-8 font-medium text-gray-900\">\n                    Slack\n                  </h4>\n                </div>\n                <p className=\"text-xs leading-5 font-normal text-gray-400 transition-all duration-700 ease-in-out group-hover:text-gray-600\">\n                  The Slack app enhances team collaboration by providing\n                  real-time messaging, file sharing, and integration with\n                  numerous tools.\n                </p>\n              </div>\n              <div className=\"group flex w-full flex-col items-start justify-center gap-3.5 rounded-xl border border-gray-200 bg-white p-5 transition-all duration-700 ease-in-out hover:border-gray-700 hover:bg-gray-50\">\n                <div className=\"inline-flex items-center justify-start gap-2\">\n                  {/* SVG removed */}\n                  <h4 className=\"text-lg leading-8 font-medium text-gray-900\">\n                    Gmail\n                  </h4>\n                </div>\n                <p className=\"text-xs leading-5 font-normal text-gray-400 transition-all duration-700 ease-in-out group-hover:text-gray-600\">\n                  The Gmail app offers convenient access to email, allowing\n                  users to manage their inbox, send messages, and integrate with\n                  other Google services on the go.\n                </p>\n              </div>\n              <div className=\"group flex w-full flex-col items-start justify-center gap-3.5 rounded-xl border border-gray-200 bg-white p-5 transition-all duration-700 ease-in-out hover:border-gray-700 hover:bg-gray-50\">\n                <div className=\"inline-flex items-center justify-start gap-2\">\n                  {/* SVG removed */}\n                  <h4 className=\"text-lg leading-8 font-medium text-gray-900\">\n                    Zapier\n                  </h4>\n                </div>\n                <p className=\"text-xs leading-5 font-normal text-gray-400 transition-all duration-700 ease-in-out group-hover:text-gray-600\">\n                  The Zapier app automates workflows by connecting your favorite\n                  apps and services to streamline repetitive tasks and boost\n                  productivity.\n                </p>\n              </div>\n              <div className=\"group flex w-full flex-col items-start justify-center gap-3.5 rounded-xl border border-gray-200 bg-white p-5 transition-all duration-700 ease-in-out hover:border-gray-700 hover:bg-gray-50\">\n                <div className=\"inline-flex items-center justify-start gap-2\">\n                  {/* SVG removed */}\n                  <h4 className=\"text-lg leading-8 font-medium text-gray-900\">\n                    Dropbox\n                  </h4>\n                </div>\n                <p className=\"text-xs leading-5 font-normal text-gray-400 transition-all duration-700 ease-in-out group-hover:text-gray-600\">\n                  The Dropbox app offers secure cloud storage and file sharing,\n                  allowing users to easily access their documents from any\n                  device, anywhere.\n                </p>\n              </div>\n              <div className=\"group flex w-full flex-col items-start justify-center gap-3.5 rounded-xl border border-gray-200 bg-white p-5 transition-all duration-700 ease-in-out hover:border-gray-700 hover:bg-gray-50\">\n                <div className=\"inline-flex items-center justify-start gap-2\">\n                  {/* SVG removed */}\n                  <h4 className=\"text-lg leading-8 font-medium text-gray-900\">\n                    Notion\n                  </h4>\n                </div>\n                <p className=\"text-xs leading-5 font-normal text-gray-400 transition-all duration-700 ease-in-out group-hover:text-gray-600\">\n                  The Notion app combines note-taking, project management, and\n                  collaboration tools in one platform, helping teams and\n                  inpiduals stay organized and productive.\n                </p>\n              </div>\n              <div className=\"group flex w-full flex-col items-start justify-center gap-3.5 rounded-xl border border-gray-200 bg-white p-5 transition-all duration-700 ease-in-out hover:border-gray-700 hover:bg-gray-50\">\n                <div className=\"inline-flex items-center justify-start gap-2\">\n                  {/* SVG removed */}\n                  <h4 className=\"text-lg leading-8 font-medium text-gray-900\">\n                    Amazon\n                  </h4>\n                </div>\n                <p className=\"text-xs leading-5 font-normal text-gray-400 transition-all duration-700 ease-in-out group-hover:text-gray-600\">\n                  The Amazon app enables users to shop for millions of products,\n                  track orders, and access exclusive deals directly from their\n                  mobile devices.\n                </p>\n              </div>\n            </div>\n          </div>\n        </div>\n      </div>\n    </section>\n  )\n}\n",
      "type": "registry:block"
    }
  ],
  "categories": [
    "marketing"
  ],
  "tier": "pro",
  "readiness": "alpha"
}