{
  "$schema": "https://ui.pitsi.com/schema/registry-item.json",
  "name": "marketing-contact-form-colorful-call-to-action-contact-blocks",
  "type": "registry:block",
  "description": "A colorful call to action contact blocks block.",
  "files": [
    {
      "path": "registry/new-york-v4/blocks/marketing/contact-form/colorful-call-to-action-contact-blocks.tsx",
      "content": "export default function ColorfulCallToActionContactBlocks() {\n  return (\n    <section className=\"py-24\">\n      <div className=\"mx-auto max-w-7xl px-4 sm:px-6 lg:px-8\">\n        <h2 className=\"font-manrope text-center text-4xl leading-10 font-bold text-indigo-600\">\n          Contact Information\n        </h2>\n        <p className=\"font-inter pt-4 text-center text-base leading-7 font-normal text-gray-700\">\n          We’re here to assist you with any questions, concerns, or feedback.\n          Whether you need support, more information.\n        </p>\n        <div className=\"grid gap-8 pt-14 lg:grid-cols-2 xl:grid-cols-3\">\n          <div className=\"order-2 flex flex-col gap-8 md:order-2 lg:order-1 xl:order-1\">\n            <div className=\"group flex items-center gap-4 rounded-2xl bg-indigo-50 p-6 transition-all duration-500 hover:bg-indigo-600\">\n              {/* SVG removed */}\n              <div className=\"font-inter\">\n                <h5 className=\"text-lg leading-7 font-medium text-black transition-all duration-500 group-hover:text-white\">\n                  Address\n                </h5>\n                <p className=\"pt-2 text-sm leading-5 font-normal text-gray-500 transition-all duration-500 group-hover:text-white\">\n                  789 Oak Lane, Lakeside, TX 54321\n                </p>\n              </div>\n            </div>\n            <div className=\"group flex items-center gap-4 rounded-2xl bg-indigo-50 p-6 transition-all duration-500 hover:bg-indigo-600\">\n              {/* SVG removed */}\n              <div className=\"font-inter\">\n                <h5 className=\"text-lg leading-7 font-medium text-black transition-all duration-500 group-hover:text-white\">\n                  Contact\n                </h5>\n                <p className=\"pt-2 text-sm leading-5 font-normal text-gray-500 transition-all duration-500 group-hover:text-white\">\n                  1800-2541-2541, 1800-14-0147\n                </p>\n              </div>\n            </div>\n            <div className=\"group flex items-center gap-4 rounded-2xl bg-indigo-50 p-6 transition-all duration-500 hover:bg-indigo-600\">\n              {/* SVG removed */}\n              <div className=\"font-inter\">\n                <h5 className=\"text-lg leading-7 font-medium text-black transition-all duration-500 group-hover:text-white\">\n                  Email\n                </h5>\n                <a className=\"text-sm leading-5 font-normal text-gray-500 transition-all duration-500 group-hover:text-white\">\n                  pagedone1234@gmail.com\n                </a>\n              </div>\n            </div>\n          </div>\n          <div className=\"order-3 col-span-full overflow-hidden rounded-2xl md:order-3 lg:order-3 xl:order-2 xl:col-span-1\">\n            <iframe\n              className=\"w-full\"\n              src=\"https://www.google.com/maps?q=Rajkot,Gujarat,India&z=13&output=embed\"\n              height={365}\n              allowFullScreen\n              loading=\"lazy\"\n              referrerPolicy=\"no-referrer-when-downgrade\"\n            ></iframe>\n          </div>\n          <div className=\"order-1 flex flex-col gap-6 md:order-1 lg:order-2 xl:order-3\">\n            <div className=\"font-inter flex flex-col gap-1.5\">\n              <label\n                htmlFor=\"\"\n                className=\"flex items-center gap-1 text-base leading-6 font-medium text-gray-600\"\n              >\n                Your Name\n                {/* SVG removed */}\n              </label>\n              <input\n                type=\"text\"\n                name=\"\"\n                id=\"\"\n                className=\"rounded-lg border border-gray-200 bg-white px-5 py-3 text-lg leading-7 font-normal text-gray-400 outline-none placeholder:text-gray-500 focus:border-gray-300\"\n                placeholder=\"Name\"\n              />\n            </div>\n            <div className=\"font-inter flex flex-col gap-1.5\">\n              <label\n                htmlFor=\"\"\n                className=\"flex items-center gap-1 text-base leading-6 font-medium text-gray-600\"\n              >\n                Email\n                {/* SVG removed */}\n              </label>\n              <input\n                type=\"email\"\n                name=\"\"\n                id=\"\"\n                className=\"rounded-lg border border-gray-200 bg-white px-5 py-3 text-lg leading-7 font-normal text-gray-400 outline-none placeholder:text-gray-500 focus:border-gray-300\"\n                placeholder=\"Email\"\n              />\n            </div>\n            <div className=\"font-inter flex flex-col gap-1.5\">\n              <label\n                htmlFor=\"\"\n                className=\"flex items-center gap-1 text-base leading-6 font-medium text-gray-600\"\n              >\n                Phone Number\n                {/* SVG removed */}\n              </label>\n              <input\n                type=\"text\"\n                name=\"\"\n                id=\"\"\n                className=\"rounded-lg border border-gray-200 bg-white px-5 py-3 text-lg leading-7 font-normal text-gray-400 outline-none placeholder:text-gray-500 focus:border-gray-300\"\n                placeholder=\"Phone\"\n              />\n            </div>\n            <button className=\"h-12 w-full rounded-2xl bg-indigo-600 text-base leading-6 font-semibold text-white shadow-sm transition-all duration-700 hover:bg-indigo-800\">\n              Submit\n            </button>\n          </div>\n        </div>\n      </div>\n    </section>\n  )\n}\n",
      "type": "registry:block"
    }
  ],
  "categories": [
    "marketing"
  ],
  "tier": "free",
  "readiness": "alpha"
}