{
  "$schema": "https://pitsiui.com/schema/registry-item.json",
  "name": "marketing-pricing-plans-pricing-cards-with-vertical-tabs",
  "type": "registry:block",
  "description": "A pricing cards with vertical tabs block.",
  "files": [
    {
      "path": "registry/new-york-v4/blocks/marketing/pricing-plans/pricing-cards-with-vertical-tabs.tsx",
      "content": "export default function PricingCardsWithVerticalTabs() {\n  return (\n    <section className=\"py-24\">\n      <div className=\"mx-auto max-w-7xl px-4 sm:px-6 lg:px-8\">\n        <div className=\"mx-auto flex w-full flex-col items-center justify-start gap-3 pb-10 sm:w-96 lg:w-full lg:gap-4 lg:pb-12\">\n          <h2 className=\"font-manrope text-center text-4xl leading-normal font-bold text-gray-900\">\n            Choose Your Plan\n          </h2>\n          <p className=\"w-full text-center text-base leading-relaxed font-normal text-gray-500 lg:max-w-4xl\">\n            Select from a variety of tailored pricing options designed to meet\n            your specific needs and budget. Whether you're an individual, small\n            business, or enterprise, our plans offer comprehensive features.\n          </p>\n        </div>\n        <div className=\"tabs mx-auto grid w-full items-center justify-center gap-9 rounded-3xl border border-indigo-300 bg-white p-5 sm:w-fit sm:p-6 lg:w-full lg:grid-cols-2 lg:items-start lg:justify-start lg:p-8\">\n          <div className=\"flex w-full flex-col items-center justify-center gap-6 lg:gap-11\">\n            <a\n              className=\"tab-active:border-transparent tab-active:bg-indigo-500 tab-active:text-white tab-active:rounded-3xl tablink active flex w-full flex-col items-start justify-start gap-2.5 rounded-2xl border border-gray-200 bg-transparent p-6 whitespace-nowrap transition-all duration-700 ease-in-out lg:p-8\"\n              data-tab=\"tabs-with-background-1\"\n              role=\"tab\"\n            >\n              <div className=\"pointer-events-none inline-flex w-full items-center justify-between gap-6\">\n                <div className=\"flex items-center justify-start gap-5\">\n                  <div className=\"iconBg tablink-active:bg-white flex h-[68px] w-[68px] items-center justify-center rounded-full bg-indigo-50 transition-all duration-700 ease-in-out\">\n                    {/* SVG removed */}\n                  </div>\n                  <div className=\"inline-flex flex-col items-start justify-start gap-0.5\">\n                    <h4 className=\"tablink-active:text-white text-xl leading-8 font-semibold text-gray-900 transition-all duration-700 ease-in-out\">\n                      Free Plan\n                    </h4>\n                    <span className=\"tablink-active:text-gray-200 text-sm leading-normal font-normal text-gray-600 transition-all duration-700 ease-in-out\">\n                      For small companies.\n                    </span>\n                  </div>\n                </div>\n                <div className=\"flex items-end justify-start\">\n                  <h2 className=\"tablink-active:text-white font-manrope text-right text-4xl leading-normal font-semibold text-black transition-all duration-700 ease-in-out\">\n                    $0\n                  </h2>\n                  <h6 className=\"tablink-active:text-white text-base leading-relaxed font-normal text-black transition-all duration-700 ease-in-out\">\n                    /Mo\n                  </h6>\n                </div>\n              </div>\n            </a>\n            <a\n              className=\"group tab-active:border-transparent tab-active:bg-indigo-500 tab-active:rounded-3xl tablink flex w-full flex-col items-start justify-start gap-2.5 rounded-2xl border border-gray-200 bg-transparent p-6 whitespace-nowrap transition-all duration-700 ease-in-out lg:p-8\"\n              data-tab=\"tabs-with-background-2\"\n              role=\"tab\"\n            >\n              <div className=\"pointer-events-none inline-flex w-full items-center justify-between gap-6\">\n                <div className=\"flex items-center justify-start gap-5\">\n                  <div className=\"iconBg flex h-[68px] w-[68px] items-center justify-center rounded-full bg-indigo-50 transition-all duration-700 ease-in-out\">\n                    {/* SVG removed */}\n                  </div>\n                  <div className=\"inline-flex flex-col items-start justify-start gap-0.5\">\n                    <h4 className=\"tablink-active:text-white text-xl leading-8 font-semibold text-gray-900 transition-all duration-700 ease-in-out\">\n                      Business Plan\n                    </h4>\n                    <span className=\"tablink-active:text-gray-200 text-sm leading-normal font-normal text-gray-600 transition-all duration-700 ease-in-out\">\n                      For small companies.\n                    </span>\n                  </div>\n                </div>\n                <div className=\"flex items-end justify-start\">\n                  <h2 className=\"tablink-active:text-white font-manrope text-right text-4xl leading-normal font-semibold text-black transition-all duration-700 ease-in-out\">\n                    $150\n                  </h2>\n                  <h6 className=\"tablink-active:text-white text-base leading-relaxed font-normal text-black transition-all duration-700 ease-in-out\">\n                    /Mo\n                  </h6>\n                </div>\n              </div>\n            </a>\n            <a\n              className=\"group tab-active:border-transparent tab-active:bg-indigo-500 tab-active:rounded-3xl tablink flex w-full flex-col items-start justify-start gap-2.5 rounded-2xl border border-gray-200 bg-transparent p-6 whitespace-nowrap transition-all duration-700 ease-in-out lg:p-8\"\n              data-tab=\"tabs-with-background-3\"\n              role=\"tab\"\n            >\n              <div className=\"pointer-events-none inline-flex w-full items-center justify-between gap-6\">\n                <div className=\"flex items-center justify-start gap-5\">\n                  <div className=\"iconBg flex h-[68px] w-[68px] items-center justify-center rounded-full bg-indigo-50 transition-all duration-700 ease-in-out\">\n                    {/* SVG removed */}\n                  </div>\n                  <div className=\"inline-flex flex-col items-start justify-start gap-0.5\">\n                    <h4 className=\"tablink-active:text-white text-xl leading-8 font-semibold text-gray-900 transition-all duration-700 ease-in-out\">\n                      Enterprise Plan\n                    </h4>\n                    <span className=\"tablink-active:text-gray-200 text-sm leading-normal font-normal text-gray-600 transition-all duration-700 ease-in-out\">\n                      For small companies.\n                    </span>\n                  </div>\n                </div>\n                <div className=\"flex items-end justify-start\">\n                  <h2 className=\"tablink-active:text-white font-manrope text-right text-4xl leading-normal font-semibold text-black transition-all duration-700 ease-in-out\">\n                    $200\n                  </h2>\n                  <h6 className=\"tablink-active:text-white text-base leading-relaxed font-normal text-black transition-all duration-700 ease-in-out\">\n                    /Mo\n                  </h6>\n                </div>\n              </div>\n            </a>\n          </div>\n          <div\n            id=\"tabs-with-background-1\"\n            role=\"tabpanel\"\n            aria-labelledby=\"tabs-with-background-item-1\"\n            className=\"tabcontent w-full\"\n          >\n            <div className=\"inline-flex w-full flex-col items-start justify-start rounded-3xl bg-indigo-500 px-4 pt-8 pb-5\">\n              <div className=\"flex w-full flex-col items-start justify-start gap-5\">\n                <div className=\"flex flex-col items-start justify-start gap-2 px-4\">\n                  <h3 className=\"font-manrope text-2xl leading-9 font-semibold text-white\">\n                    Free Plan\n                  </h3>\n                  <span className=\"text-xs leading-normal font-normal text-gray-200\">\n                    For small companies.\n                  </span>\n                </div>\n                <div className=\"flex w-full flex-col items-start justify-start rounded-2xl bg-white p-3.5\">\n                  <div className=\"flex w-full flex-col items-start justify-start gap-8\">\n                    <div className=\"flex w-full flex-col items-start justify-start gap-5\">\n                      <div className=\"inline-flex w-full items-center justify-start gap-3\">\n                        <h2 className=\"font-manrope text-center text-4xl leading-normal font-bold text-gray-900\">\n                          $0\n                        </h2>\n                        <h4 className=\"text-center text-xl leading-8 font-normal text-gray-500\">\n                          | Month\n                        </h4>\n                      </div>\n                      <ul className=\"flex w-full flex-col items-start justify-start gap-6\">\n                        <li className=\"inline-flex items-center justify-start gap-3\">\n                          {/* SVG removed */}\n                          <h6 className=\"text-base leading-relaxed font-normal text-gray-800\">\n                            AI advisor for a day\n                          </h6>\n                        </li>\n                        <li className=\"inline-flex items-center justify-start gap-3\">\n                          {/* SVG removed */}\n                          <h6 className=\"text-base leading-relaxed font-normal text-gray-800\">\n                            2 auto tracking\n                          </h6>\n                        </li>\n                        <li className=\"inline-flex items-center justify-start gap-3\">\n                          {/* SVG removed */}\n                          <h6 className=\"text-base leading-relaxed font-normal text-gray-800\">\n                            7 Day transaction clearing{\" \"}\n                          </h6>\n                        </li>\n                        <li className=\"inline-flex items-center justify-start gap-3\">\n                          {/* SVG removed */}\n                          <h6 className=\"text-base leading-relaxed font-normal text-gray-800\">\n                            24/7 Customer support\n                          </h6>\n                        </li>\n                      </ul>\n                    </div>\n                    <button className=\"flex w-full items-center justify-center rounded-full bg-indigo-500 px-5 py-2.5 shadow-[0px_1px_2px_0px_rgba(16,_24,_40,_0.05)] transition-all duration-700 ease-in-out hover:bg-indigo-600\">\n                      <span className=\"px-2 py-px text-base leading-relaxed font-semibold text-white\">\n                        Purchase Plan\n                      </span>\n                    </button>\n                  </div>\n                </div>\n              </div>\n            </div>\n          </div>\n          <div\n            id=\"tabs-with-background-2\"\n            role=\"tabpanel\"\n            aria-labelledby=\"tabs-with-background-item-2\"\n            className=\"tabcontent w-full\"\n          >\n            <div className=\"inline-flex w-full flex-col items-start justify-start rounded-3xl bg-indigo-500 px-4 pt-8 pb-5\">\n              <div className=\"flex w-full flex-col items-start justify-start gap-5\">\n                <div className=\"flex flex-col items-start justify-start gap-2 px-4\">\n                  <h3 className=\"font-manrope text-2xl leading-9 font-semibold text-white\">\n                    Business Plan\n                  </h3>\n                  <span className=\"text-xs leading-normal font-normal text-gray-200\">\n                    For small companies.\n                  </span>\n                </div>\n                <div className=\"flex w-full flex-col items-start justify-start rounded-2xl bg-white p-3.5\">\n                  <div className=\"flex w-full flex-col items-start justify-start gap-8\">\n                    <div className=\"flex w-full flex-col items-start justify-start gap-5\">\n                      <div className=\"inline-flex w-full items-center justify-start gap-3\">\n                        <h2 className=\"font-manrope text-center text-4xl leading-normal font-bold text-gray-900\">\n                          $150\n                        </h2>\n                        <h4 className=\"text-center text-xl leading-8 font-normal text-gray-500\">\n                          | Month\n                        </h4>\n                      </div>\n                      <ul className=\"flex w-full flex-col items-start justify-start gap-6\">\n                        <li className=\"inline-flex items-center justify-start gap-3\">\n                          {/* SVG removed */}\n                          <h6 className=\"text-base leading-relaxed font-normal text-gray-800\">\n                            AI advisor for a day\n                          </h6>\n                        </li>\n                        <li className=\"inline-flex items-center justify-start gap-3\">\n                          {/* SVG removed */}\n                          <h6 className=\"text-base leading-relaxed font-normal text-gray-800\">\n                            2 auto tracking\n                          </h6>\n                        </li>\n                        <li className=\"inline-flex items-center justify-start gap-3\">\n                          {/* SVG removed */}\n                          <h6 className=\"text-base leading-relaxed font-normal text-gray-800\">\n                            7 Day transaction clearing{\" \"}\n                          </h6>\n                        </li>\n                        <li className=\"inline-flex items-center justify-start gap-3\">\n                          {/* SVG removed */}\n                          <h6 className=\"text-base leading-relaxed font-normal text-gray-800\">\n                            24/7 Customer support\n                          </h6>\n                        </li>\n                      </ul>\n                    </div>\n                    <button className=\"flex w-full items-center justify-center rounded-full bg-indigo-500 px-5 py-2.5 shadow-[0px_1px_2px_0px_rgba(16,_24,_40,_0.05)] transition-all duration-700 ease-in-out hover:bg-indigo-600\">\n                      <span className=\"px-2 py-px text-base leading-relaxed font-semibold text-white\">\n                        Purchase Plan\n                      </span>\n                    </button>\n                  </div>\n                </div>\n              </div>\n            </div>\n          </div>\n          <div\n            id=\"tabs-with-background-3\"\n            role=\"tabpanel\"\n            aria-labelledby=\"tabs-with-background-item-3\"\n            className=\"tabcontent w-full\"\n          >\n            <div className=\"inline-flex w-full flex-col items-start justify-start rounded-3xl bg-indigo-500 px-4 pt-8 pb-5\">\n              <div className=\"flex w-full flex-col items-start justify-start gap-5\">\n                <div className=\"flex flex-col items-start justify-start gap-2 px-4\">\n                  <h3 className=\"font-manrope text-2xl leading-9 font-semibold text-white\">\n                    Enterprise Plan\n                  </h3>\n                  <span className=\"text-xs leading-normal font-normal text-gray-200\">\n                    For small companies.\n                  </span>\n                </div>\n                <div className=\"flex w-full flex-col items-start justify-start rounded-2xl bg-white p-3.5\">\n                  <div className=\"flex w-full flex-col items-start justify-start gap-8\">\n                    <div className=\"flex w-full flex-col items-start justify-start gap-5\">\n                      <div className=\"inline-flex w-full items-center justify-start gap-3\">\n                        <h2 className=\"font-manrope text-center text-4xl leading-normal font-bold text-gray-900\">\n                          $200\n                        </h2>\n                        <h4 className=\"text-center text-xl leading-8 font-normal text-gray-500\">\n                          | Month\n                        </h4>\n                      </div>\n                      <ul className=\"flex w-full flex-col items-start justify-start gap-6\">\n                        <li className=\"inline-flex items-center justify-start gap-3\">\n                          {/* SVG removed */}\n                          <h6 className=\"text-base leading-relaxed font-normal text-gray-800\">\n                            AI advisor for a day\n                          </h6>\n                        </li>\n                        <li className=\"inline-flex items-center justify-start gap-3\">\n                          {/* SVG removed */}\n                          <h6 className=\"text-base leading-relaxed font-normal text-gray-800\">\n                            2 auto tracking\n                          </h6>\n                        </li>\n                        <li className=\"inline-flex items-center justify-start gap-3\">\n                          {/* SVG removed */}\n                          <h6 className=\"text-base leading-relaxed font-normal text-gray-800\">\n                            7 Day transaction clearing{\" \"}\n                          </h6>\n                        </li>\n                        <li className=\"inline-flex items-center justify-start gap-3\">\n                          {/* SVG removed */}\n                          <h6 className=\"text-base leading-relaxed font-normal text-gray-800\">\n                            24/7 Customer support\n                          </h6>\n                        </li>\n                      </ul>\n                    </div>\n                    <button className=\"flex w-full items-center justify-center rounded-full bg-indigo-500 px-5 py-2.5 shadow-[0px_1px_2px_0px_rgba(16,_24,_40,_0.05)] transition-all duration-700 ease-in-out hover:bg-indigo-600\">\n                      <span className=\"px-2 py-px text-base leading-relaxed font-semibold text-white\">\n                        Purchase Plan\n                      </span>\n                    </button>\n                  </div>\n                </div>\n              </div>\n            </div>\n          </div>\n        </div>\n      </div>\n    </section>\n  )\n}\n",
      "type": "registry:block"
    }
  ],
  "categories": [
    "marketing"
  ],
  "tier": "pro",
  "readiness": "beta"
}